unilakedocstheme/__init__.py
unilakedocstheme/ext.py
unilakedocstheme/page_context.py
unilakedocstheme/paths.py
unilakedocstheme/version.py
unilakedocstheme/theme/starlingxdocs/footer.html
unilakedocstheme/theme/starlingxdocs/header.html
unilakedocstheme/theme/starlingxdocs/sidebartoc_menu.html
unilakedocstheme/theme/starlingxdocs/sidebartoc_menu_apiref.html
unilakedocstheme/theme/starlingxdocs/stx_search.html
unilakedocstheme/theme/starlingxdocs/stx_search_install.html
unilakedocstheme/theme/starlingxdocs/stx_search_mobile.html
unilakedocstheme/theme/starlingxdocs/theme.conf
unilakedocstheme/theme/starlingxdocs/titlerow.html
unilakedocstheme/theme/starlingxdocs/static/css/combined.css
unilakedocstheme/theme/starlingxdocs/static/images/StarlingX_Logo_RGB_Horizontal_2color.png
unilakedocstheme/theme/starlingxdocs/static/images/StarlingX_Logo_RGB_Horizontal_2color.svg
unilakedocstheme/theme/starlingxdocs/static/images/StarlingX_Logo_RGB_Stacked_2color.png
unilakedocstheme/theme/starlingxdocs/static/images/StarlingX_Logo_RGB_Stacked_2color.svg
unilakedocstheme/theme/starlingxdocs/static/images/logo-full.png
unilakedocstheme/theme/starlingxdocs/static/images/logo-full.svg
unilakedocstheme/theme/starlingxdocs/static/images/logo-vert.png
unilakedocstheme/theme/starlingxdocs/static/images/logo-vert.svg
unilakedocstheme/theme/starlingxdocs_pdf/logo-full.png
unilakedocstheme/theme/starlingxdocs_pdf/logo-full.svg
unilakedocstheme/theme/starlingxdocs_pdf/pdftheme.sty
unilakedocstheme/theme/unilakedocs/css.html
unilakedocstheme/theme/unilakedocs/footer.html
unilakedocstheme/theme/unilakedocs/header.html
unilakedocstheme/theme/unilakedocs/layout.html
unilakedocstheme/theme/unilakedocs/license_cc.html
unilakedocstheme/theme/unilakedocs/localtoc.html
unilakedocstheme/theme/unilakedocs/os_search.html
unilakedocstheme/theme/unilakedocs/os_search_install.html
unilakedocstheme/theme/unilakedocs/os_search_mobile.html
unilakedocstheme/theme/unilakedocs/script_footer.html
unilakedocstheme-1.1.4.dist-info/AUTHORS
unilakedocstheme-1.1.4.dist-info/METADATA
unilakedocstheme-1.1.4.dist-info/WHEEL
unilakedocstheme-1.1.4.dist-info/pbr.json
unilakedocstheme-1.1.4.dist-info/top_level.txt
unilakedocstheme-1.1.4.dist-info/RECORD
